solapi/__init__.py
solapi/auth.py
solapi/config.py
solapi/request.py
solapi/storage.py
solapi/sms/__init__.py
solapi/sms/message.py
solapi_sms-0.1.0.dist-info/LICENSE
solapi_sms-0.1.0.dist-info/METADATA
solapi_sms-0.1.0.dist-info/WHEEL
solapi_sms-0.1.0.dist-info/top_level.txt
solapi_sms-0.1.0.dist-info/RECORD
